cisco_nso_restconf/__init__.py
cisco_nso_restconf/client.py
cisco_nso_restconf/devices.py
cisco_nso_restconf/query.py
cisco_nso_restconf-1.0.5.dist-info/METADATA
cisco_nso_restconf-1.0.5.dist-info/WHEEL
cisco_nso_restconf-1.0.5.dist-info/licenses/LICENSE
cisco_nso_restconf-1.0.5.dist-info/RECORD
