Metadata-Version: 2.4
Name: cisco-nso-restconf
Version: 1.0.5
Summary: A Python client library for interacting with the Cisco NSO RESTCONF API
Author-email: Darren Bono <dbono215@gmail.com>
License-Expression: MIT
License-File: LICENSE
Requires-Python: <4.0,>=3.8.1
Requires-Dist: requests>=2.32.3
